AUTHORS.rst
CONTRIBUTING.rst
HISTORY.rst
LICENSE
MANIFEST.in
README.rst
setup.cfg
setup.py
docs/Makefile
docs/authors.rst
docs/conf.py
docs/contributing.rst
docs/history.rst
docs/index.rst
docs/installation.rst
docs/make.bat
docs/readme.rst
docs/usage.rst
gridic/__init__.py
gridic/config.py
gridic/gridic.py
gridic/index.html
gridic.egg-info/PKG-INFO
gridic.egg-info/SOURCES.txt
gridic.egg-info/dependency_links.txt
gridic.egg-info/not-zip-safe
gridic.egg-info/requires.txt
gridic.egg-info/top_level.txt
gridic/static/.DS_Store
gridic/static/css/gridic.css
gridic/static/js/gridic.js
gridic/static/js/underscore.js
tests/__init__.py
tests/test_gridic.py