Metadata-Version: 1.1
Name: gridic
Version: 0.1.1
Summary: A grid-like interface to creating simple music
Home-page: https://github.com/elvisds/gridic
Author: Elvis D'Souza
Author-email: me@elvis.co.in
License: BSD
Keywords: gridic
Platform: UNKNOWN
Classifier: Development Status :: 2 - Pre-Alpha
Classifier: Intended Audience :: Developers
Classifier: License :: OSI Approved :: BSD License
Classifier: Natural Language :: English
Classifier: Programming Language :: Python :: 2
Classifier: Programming Language :: Python :: 2.6
Classifier: Programming Language :: Python :: 2.7
Classifier: Programming Language :: Python :: 3
Classifier: Programming Language :: Python :: 3.3
Classifier: Programming Language :: Python :: 3.4
